zddns/__init__.py
zddns/app.py
zddns/cli.py
zddns/cloudflare.py
zddns/config.py
zddns/ip_discovery.py
zddns-0.1.0.dist-info/LICENSE
zddns-0.1.0.dist-info/METADATA
zddns-0.1.0.dist-info/WHEEL
zddns-0.1.0.dist-info/entry_points.txt
zddns-0.1.0.dist-info/RECORD
