Metadata-Version: 2.1
Name: zddns
Version: 0.1.0
Summary: Update Cloudflare DNS records with your network's external IP address
License: MIT
Author: User
Author-email: user@example.com
Requires-Python: >=3.9
Classifier: License :: OSI Approved :: MIT License
Classifier: Programming Language :: Python :: 3
Classifier: Programming Language :: Python :: 3.9
Classifier: Programming Language :: Python :: 3.10
Classifier: Programming Language :: Python :: 3.11
Requires-Dist: click (>=8.1.0)
Requires-Dist: pyyaml (>=6.0)
Requires-Dist: requests (>=2.28.0)
